yzm_log/__init__.py
yzm_log-0.0.2.dist-info/METADATA
yzm_log-0.0.2.dist-info/WHEEL
yzm_log-0.0.2.dist-info/licenses/LICENSE
yzm_log-0.0.2.dist-info/RECORD
